pysll/__init__.py
pysll/constellation.py
pysll/decoders.py
pysll/exceptions.py
pysll/feature_flags.py
pysll/functions.py
pysll/models.py
pysll/parsers.py
pysll/unit_operations.py
pysll/utils.py
pysll-0.3.5.dist-info/METADATA
pysll-0.3.5.dist-info/WHEEL
pysll-0.3.5.dist-info/licenses/LICENSE
pysll-0.3.5.dist-info/RECORD
