Metadata-Version: 2.4
Name: pysll
Version: 0.3.5
Author-email: Bruno Lange <bruno.lange@emeraldcloudlab.com>, Robert Teed <robert@emeraldcloudlab.com>
License-File: LICENSE
Requires-Python: >=3.10
Requires-Dist: backoff>=1.10.0
Requires-Dist: requests>=2.22.0
Requires-Dist: rollbar>=0.14.7
Requires-Dist: xmltodict>=0.13.0
Provides-Extra: numpy
Requires-Dist: numpy>=1.26.4; extra == 'numpy'
